setup.cfg
setup.py
ds_greytheory/__init__.py
ds_greytheory.egg-info/PKG-INFO
ds_greytheory.egg-info/SOURCES.txt
ds_greytheory.egg-info/dependency_links.txt
ds_greytheory.egg-info/not-zip-safe
ds_greytheory.egg-info/top_level.txt