Metadata-Version: 1.0
Name: ds-greytheory
Version: 0.2
Summary: Grey Theory models and tools
Home-page: UNKNOWN
Author: Gustavo Jorge Martins de Aguiar
Author-email: gustavoaguiar@id.uff.br
License: UNKNOWN
Platform: UNKNOWN
